<?xml version="1.0" encoding="UTF-8"?>
<mxGraphModel dx="1426" dy="774" grid="1" gridSize="10" guides="1" tooltips="1" connect="1" arrows="1" fold="1" page="1" pageScale="1" pageWidth="850" pageHeight="1100" background="#ffffff" math="0" shadow="0"><root><mxCell id="0"/><mxCell id="1" parent="0"/><mxCell id="1a8abee3a6cfdf20-38" value="" style="verticalLabelPosition=bottom;html=1;verticalAlign=top;strokeWidth=1;dashed=0;shape=mxgraph.aws3d.flatDoubleEdge;fillColor=#000000;aspect=fixed;rounded=1;shadow=0;comic=0;fontFamily=Verdana;fontSize=12;fontColor=#000000;flipV=1;" parent="1" vertex="1"><mxGeometry x="710" y="912.5" width="387" height="221" as="geometry"/></mxCell><mxCell id="1a8abee3a6cfdf20-18" value="" style="verticalLabelPosition=bottom;html=1;verticalAlign=top;strokeWidth=1;dashed=0;shape=mxgraph.aws3d.application_server;fillColor=#ECECEC;strokeColor=#5E5E5E;aspect=fixed;rounded=1;shadow=0;comic=0;fontSize=12;fontColor=#000000;" parent="1" vertex="1"><mxGeometry x="743" y="994.5" width="123" height="124" as="geometry"/></mxCell><mxCell id="d5ac148becb70bc-8" value="" style="verticalLabelPosition=bottom;html=1;verticalAlign=top;strokeWidth=1;dashed=0;shape=mxgraph.aws3d.dashedArrowlessEdge;fillColor=#000000;aspect=fixed;rounded=1;shadow=0;comic=0;fontFamily=Verdana;fontSize=12;fontColor=#000000;" parent="1" vertex="1"><mxGeometry x="840" y="564" width="501" height="286" as="geometry"/></mxCell><mxCell id="d5ac148becb70bc-9" value="" style="verticalLabelPosition=bottom;html=1;verticalAlign=top;strokeWidth=1;dashed=0;shape=mxgraph.aws3d.dashedArrowlessEdge;fillColor=#000000;aspect=fixed;rounded=1;shadow=0;comic=0;fontFamily=Verdana;fontSize=12;fontColor=#000000;" parent="1" vertex="1"><mxGeometry x="592" y="705" width="500" height="285" as="geometry"/></mxCell><mxCell id="d5ac148becb70bc-10" value="" style="verticalLabelPosition=bottom;html=1;verticalAlign=top;strokeWidth=1;dashed=0;shape=mxgraph.aws3d.dashedArrowlessEdge;fillColor=#000000;aspect=fixed;rounded=1;shadow=0;comic=0;fontFamily=Verdana;fontSize=12;fontColor=#000000;flipV=1;" parent="1" vertex="1"><mxGeometry x="592" y="564" width="248" height="141" as="geometry"/></mxCell><mxCell id="d5ac148becb70bc-12" value="" style="verticalLabelPosition=bottom;html=1;verticalAlign=top;strokeWidth=1;dashed=0;shape=mxgraph.aws3d.dashedArrowlessEdge;fillColor=#000000;aspect=fixed;rounded=1;shadow=0;comic=0;fontFamily=Verdana;fontSize=12;fontColor=#000000;flipV=1;" parent="1" vertex="1"><mxGeometry x="1097" y="847" width="249" height="142" as="geometry"/></mxCell><mxCell id="k9gY9WLBbs6gPDYeEHhx-3" value="" style="verticalLabelPosition=bottom;html=1;verticalAlign=top;strokeWidth=1;align=center;outlineConnect=0;dashed=0;outlineConnect=0;shape=mxgraph.aws3d.end_user;strokeColor=none;fillColor=#777777;aspect=fixed;" vertex="1" parent="1"><mxGeometry x="743" y="1016.5" width="49" height="100.46" as="geometry"/></mxCell><mxCell id="k9gY9WLBbs6gPDYeEHhx-6" value="" style="verticalLabelPosition=bottom;html=1;verticalAlign=top;strokeWidth=1;dashed=0;shape=mxgraph.aws3d.flatDoubleEdge;fillColor=#000000;aspect=fixed;rounded=1;shadow=0;comic=0;fontFamily=Verdana;fontSize=12;fontColor=#000000;flipV=1;" vertex="1" parent="1"><mxGeometry x="549" y="811" width="387" height="221" as="geometry"/></mxCell><mxCell id="k9gY9WLBbs6gPDYeEHhx-7" value="" style="verticalLabelPosition=bottom;html=1;verticalAlign=top;strokeWidth=1;dashed=0;shape=mxgraph.aws3d.application_server;fillColor=#ECECEC;strokeColor=#5E5E5E;aspect=fixed;rounded=1;shadow=0;comic=0;fontSize=12;fontColor=#000000;" vertex="1" parent="1"><mxGeometry x="582" y="893" width="123" height="124" as="geometry"/></mxCell><mxCell id="k9gY9WLBbs6gPDYeEHhx-8" value="" style="verticalLabelPosition=bottom;html=1;verticalAlign=top;strokeWidth=1;align=center;outlineConnect=0;dashed=0;outlineConnect=0;shape=mxgraph.aws3d.end_user;strokeColor=none;fillColor=#777777;aspect=fixed;" vertex="1" parent="1"><mxGeometry x="582" y="915" width="49" height="100.46" as="geometry"/></mxCell><mxCell id="k9gY9WLBbs6gPDYeEHhx-9" value="" style="verticalLabelPosition=bottom;html=1;verticalAlign=top;strokeWidth=1;dashed=0;shape=mxgraph.aws3d.flatDoubleEdge;fillColor=#000000;aspect=fixed;rounded=1;shadow=0;comic=0;fontFamily=Verdana;fontSize=12;fontColor=#000000;flipV=1;" vertex="1" parent="1"><mxGeometry x="406.5" y="667" width="387" height="221" as="geometry"/></mxCell><mxCell id="k9gY9WLBbs6gPDYeEHhx-10" value="" style="verticalLabelPosition=bottom;html=1;verticalAlign=top;strokeWidth=1;dashed=0;shape=mxgraph.aws3d.application_server;fillColor=#ECECEC;strokeColor=#5E5E5E;aspect=fixed;rounded=1;shadow=0;comic=0;fontSize=12;fontColor=#000000;" vertex="1" parent="1"><mxGeometry x="439.5" y="749" width="123" height="124" as="geometry"/></mxCell><mxCell id="k9gY9WLBbs6gPDYeEHhx-11" value="" style="verticalLabelPosition=bottom;html=1;verticalAlign=top;strokeWidth=1;align=center;outlineConnect=0;dashed=0;outlineConnect=0;shape=mxgraph.aws3d.end_user;strokeColor=none;fillColor=#777777;aspect=fixed;" vertex="1" parent="1"><mxGeometry x="439.5" y="771" width="49" height="100.46" as="geometry"/></mxCell><mxCell id="k9gY9WLBbs6gPDYeEHhx-12" value="" style="verticalLabelPosition=bottom;html=1;verticalAlign=top;strokeWidth=1;align=center;outlineConnect=0;dashed=0;outlineConnect=0;shape=mxgraph.aws3d.application;fillColor=#4286c5;strokeColor=#57A2D8;aspect=fixed;" vertex="1" parent="1"><mxGeometry x="688.5" y="642.5" width="63" height="70" as="geometry"/></mxCell><mxCell id="k9gY9WLBbs6gPDYeEHhx-13" value="" style="verticalLabelPosition=bottom;html=1;verticalAlign=top;strokeWidth=1;align=center;outlineConnect=0;dashed=0;outlineConnect=0;shape=mxgraph.aws3d.application;fillColor=#4286c5;strokeColor=#57A2D8;aspect=fixed;" vertex="1" parent="1"><mxGeometry x="720.5" y="677.5" width="62" height="68.8" as="geometry"/></mxCell><mxCell id="k9gY9WLBbs6gPDYeEHhx-14" value="" style="verticalLabelPosition=bottom;html=1;verticalAlign=top;strokeWidth=1;align=center;outlineConnect=0;dashed=0;outlineConnect=0;shape=mxgraph.aws3d.application2;fillColor=#86E83A;strokeColor=#B0F373;aspect=fixed;" vertex="1" parent="1"><mxGeometry x="859" y="793" width="62" height="53" as="geometry"/></mxCell><mxCell id="k9gY9WLBbs6gPDYeEHhx-15" value="" style="verticalLabelPosition=bottom;html=1;verticalAlign=top;strokeWidth=1;align=center;outlineConnect=0;dashed=0;outlineConnect=0;shape=mxgraph.aws3d.ami2;aspect=fixed;fillColor=#FF9900;strokeColor=#ffffff;" vertex="1" parent="1"><mxGeometry x="993" y="912.5" width="74" height="50" as="geometry"/></mxCell><mxCell id="k9gY9WLBbs6gPDYeEHhx-16" value="" style="verticalLabelPosition=bottom;html=1;verticalAlign=top;strokeWidth=1;align=center;outlineConnect=0;dashed=0;outlineConnect=0;shape=mxgraph.aws3d.secureConnection;fillColor=#000000;strokeColor=#ffffff;aspect=fixed;" vertex="1" parent="1"><mxGeometry x="620" y="729.5" width="56.99999999999999" height="34" as="geometry"/></mxCell><mxCell id="k9gY9WLBbs6gPDYeEHhx-17" value="" style="verticalLabelPosition=bottom;html=1;verticalAlign=top;strokeWidth=1;align=center;outlineConnect=0;dashed=0;outlineConnect=0;shape=mxgraph.aws3d.secureConnection;fillColor=#000000;strokeColor=#ffffff;aspect=fixed;" vertex="1" parent="1"><mxGeometry x="785" y="863.5" width="56.99999999999999" height="34" as="geometry"/></mxCell><mxCell id="k9gY9WLBbs6gPDYeEHhx-18" value="" style="verticalLabelPosition=bottom;html=1;verticalAlign=top;strokeWidth=1;align=center;outlineConnect=0;dashed=0;outlineConnect=0;shape=mxgraph.aws3d.secureConnection;fillColor=#000000;strokeColor=#ffffff;aspect=fixed;" vertex="1" parent="1"><mxGeometry x="930" y="977.5" width="56.99999999999999" height="34" as="geometry"/></mxCell><mxCell id="k9gY9WLBbs6gPDYeEHhx-26" value="" style="verticalLabelPosition=bottom;html=1;verticalAlign=top;strokeWidth=1;dashed=0;shape=mxgraph.aws3d.dashedArrowlessEdge;fillColor=#000000;aspect=fixed;rounded=1;shadow=0;comic=0;fontFamily=Verdana;fontSize=12;fontColor=#000000;" vertex="1" parent="1"><mxGeometry x="1200" y="470" width="386" height="220" as="geometry"/></mxCell><mxCell id="k9gY9WLBbs6gPDYeEHhx-27" value="" style="verticalLabelPosition=bottom;html=1;verticalAlign=top;strokeWidth=1;dashed=0;shape=mxgraph.aws3d.dashedArrowlessEdge;fillColor=#000000;aspect=fixed;rounded=1;shadow=0;comic=0;fontFamily=Verdana;fontSize=12;fontColor=#000000;" vertex="1" parent="1"><mxGeometry x="1000" y="594" width="380" height="217" as="geometry"/></mxCell><mxCell id="k9gY9WLBbs6gPDYeEHhx-28" value="" style="verticalLabelPosition=bottom;html=1;verticalAlign=top;strokeWidth=1;dashed=0;shape=mxgraph.aws3d.dashedArrowlessEdge;fillColor=#000000;aspect=fixed;rounded=1;shadow=0;comic=0;fontFamily=Verdana;fontSize=12;fontColor=#000000;flipV=1;" vertex="1" parent="1"><mxGeometry x="980" y="470" width="216" height="123" as="geometry"/></mxCell><mxCell id="k9gY9WLBbs6gPDYeEHhx-29" value="" style="verticalLabelPosition=bottom;html=1;verticalAlign=top;strokeWidth=1;dashed=0;shape=mxgraph.aws3d.dashedArrowlessEdge;fillColor=#000000;aspect=fixed;rounded=1;shadow=0;comic=0;fontFamily=Verdana;fontSize=12;fontColor=#000000;flipV=1;" vertex="1" parent="1"><mxGeometry x="1385" y="700" width="193" height="110" as="geometry"/></mxCell><mxCell id="k9gY9WLBbs6gPDYeEHhx-30" value="" style="verticalLabelPosition=bottom;html=1;verticalAlign=top;strokeWidth=1;dashed=0;shape=mxgraph.aws3d.flatDoubleEdge;fillColor=#000000;aspect=fixed;rounded=1;shadow=0;comic=0;fontFamily=Verdana;fontSize=12;fontColor=#000000;flipV=1;" vertex="1" parent="1"><mxGeometry x="1050" y="677.5" width="280" height="160" as="geometry"/></mxCell><mxCell id="k9gY9WLBbs6gPDYeEHhx-38" value="" style="verticalLabelPosition=bottom;html=1;verticalAlign=top;strokeWidth=1;align=center;outlineConnect=0;dashed=0;outlineConnect=0;shape=mxgraph.aws3d.secureConnection;fillColor=#000000;strokeColor=#ffffff;aspect=fixed;" vertex="1" parent="1"><mxGeometry x="1161.5" y="739" width="56.99999999999999" height="34" as="geometry"/></mxCell><mxCell id="k9gY9WLBbs6gPDYeEHhx-39" value="" style="verticalLabelPosition=bottom;html=1;verticalAlign=top;strokeWidth=1;align=center;outlineConnect=0;dashed=0;outlineConnect=0;shape=mxgraph.aws3d.s3;fillColor=#ECECEC;strokeColor=#5E5E5E;aspect=fixed;" vertex="1" parent="1"><mxGeometry x="806" y="558" width="231.5" height="239" as="geometry"/></mxCell><mxCell id="k9gY9WLBbs6gPDYeEHhx-40" value="" style="verticalLabelPosition=bottom;html=1;verticalAlign=top;strokeWidth=1;align=center;outlineConnect=0;dashed=0;outlineConnect=0;shape=mxgraph.aws3d.s3;fillColor=#ECECEC;strokeColor=#5E5E5E;aspect=fixed;" vertex="1" parent="1"><mxGeometry x="1098.5" y="430.5" width="231.5" height="239" as="geometry"/></mxCell><mxCell id="k9gY9WLBbs6gPDYeEHhx-43" value="Each organization encrypts their data with a separate key,&lt;br style=&quot;font-size: 25px&quot;&gt;so nobody, can read it (even storage server can't)&lt;br style=&quot;font-size: 25px&quot;&gt;" style="text;strokeColor=none;fillColor=none;fontSize=25;fontStyle=3;verticalAlign=middle;align=center;rotation=35;labelBackgroundColor=none;html=1;textOpacity=70;fontColor=#000000;" vertex="1" parent="1"><mxGeometry x="631" y="873" width="205" height="45" as="geometry"/></mxCell><mxCell id="k9gY9WLBbs6gPDYeEHhx-44" value="Data is copied to a second location, &lt;br&gt;on different server, in different country&lt;br&gt;(there could be multiple locations)&lt;br style=&quot;font-size: 25px&quot;&gt;" style="text;strokeColor=none;fillColor=none;fontSize=25;fontStyle=3;verticalAlign=middle;align=center;rotation=35;labelBackgroundColor=none;html=1;textOpacity=70;fontColor=#000000;" vertex="1" parent="1"><mxGeometry x="1030" y="766" width="205" height="45" as="geometry"/></mxCell><mxCell id="k9gY9WLBbs6gPDYeEHhx-45" value="Backup is prepared and sent using our &quot;Bahub&quot; &lt;br&gt;application that is automatically preparing &lt;br&gt;backups without any human interaction&lt;br style=&quot;font-size: 25px&quot;&gt;" style="text;strokeColor=none;fillColor=none;fontSize=25;fontStyle=3;verticalAlign=middle;align=center;rotation=35;labelBackgroundColor=none;html=1;textOpacity=70;fontColor=#000000;" vertex="1" parent="1"><mxGeometry x="422" y="1033" width="134" height="80" as="geometry"/></mxCell><mxCell id="k9gY9WLBbs6gPDYeEHhx-46" value="" style="verticalLabelPosition=bottom;html=1;verticalAlign=top;strokeWidth=1;align=center;outlineConnect=0;dashed=0;outlineConnect=0;shape=mxgraph.aws3d.worker;fillColor=#ECECEC;strokeColor=#5E5E5E;aspect=fixed;labelBackgroundColor=none;fontSize=25;fontColor=#000000;" vertex="1" parent="1"><mxGeometry x="390" y="848" width="74" height="50" as="geometry"/></mxCell><mxCell id="k9gY9WLBbs6gPDYeEHhx-47" value="" style="verticalLabelPosition=bottom;html=1;verticalAlign=top;strokeWidth=1;align=center;outlineConnect=0;dashed=0;outlineConnect=0;shape=mxgraph.aws3d.worker;fillColor=#ECECEC;strokeColor=#5E5E5E;aspect=fixed;labelBackgroundColor=none;fontSize=25;fontColor=#000000;" vertex="1" parent="1"><mxGeometry x="532.5" y="994.5" width="74" height="50" as="geometry"/></mxCell><mxCell id="k9gY9WLBbs6gPDYeEHhx-48" value="" style="verticalLabelPosition=bottom;html=1;verticalAlign=top;strokeWidth=1;align=center;outlineConnect=0;dashed=0;outlineConnect=0;shape=mxgraph.aws3d.worker;fillColor=#ECECEC;strokeColor=#5E5E5E;aspect=fixed;labelBackgroundColor=none;fontSize=25;fontColor=#000000;" vertex="1" parent="1"><mxGeometry x="696.5" y="1098.5" width="74" height="50" as="geometry"/></mxCell></root></mxGraphModel>